pazer_logger_python/__init__.py
test/__init__.py
pazer_logger_python-0.4.1.dist-info/LICENSE
pazer_logger_python-0.4.1.dist-info/METADATA
pazer_logger_python-0.4.1.dist-info/WHEEL
pazer_logger_python-0.4.1.dist-info/top_level.txt
pazer_logger_python-0.4.1.dist-info/RECORD
