Metadata-Version: 2.1
Name: pazer_logger_python
Version: 0.4.1
Summary: Pazer Logger - Python
Author: David Kim
Author-email: David Kim <woody@woody.co.kr>
Project-URL: Homepage, https://github.com/pazer-app/pazer_logger_python
Project-URL: Bug Tracker, https://github.com/pazer-app/pazer_logger_python/issues
Keywords: pazer,logger
Classifier: Programming Language :: Python :: 3
Classifier: License :: OSI Approved :: MIT License
Classifier: Operating System :: OS Independent
Requires-Python: >=3.7
License-File: LICENSE
